Workbook
Name SegmentaçãodeDados_DATA: #N/A
Name SegmentaçãodeDados_IMPOSTOS: #N/A

Sheet TITULAR
G4: 1. DADOS DO TÍTULAR
G5: Preencha os dados da sua pessoa física abaixo
G8: Nome | L8: Aurora Valentina Silveira
G9: CPF | L9: 0
G10: NASCIMENTO | L10: 32907
G11: TÍTULO DE ELEITOR | L11: 0
G12: CÔNJUGE | L12: SIM
G13: RUA | L13: Rua neve na Bahia
G14: CEP | L14: 2020202020
G15: TELEFONE | L15: 101010100
G16: CELULAR | L16: 10101010
G17: EMAIL | L17: aurora.bahianeve@outlot.com.br
G18: HOUVE ALTERAÇÕES DA ENTREGA ANTERIOR | L18: NÃO
G19: POSSUI DEPENDENTE | L19: SIM
G20: RESIDENTE DO EXTERIOR | L20: NÃO

Sheet INFORMES
G4: 2. INFORMES DE RENDIMENTO BANCÁRIOS
G5: Preencha com os seus dados atuais de cada banco
G8: TOTAL | I8: =L12+L17+L26 -> 518000
G10: 1° Banco
G11: BANCO | L11: 102 - XP Investimentos CCTVM S.A.
G12: VALOR ATUAL | L12: 20000
G13: ANEXO
G15: 2° Banco
G16: BANCO | L16: 208 - Banco BTG Pactual
G17: VALOR ATUAL | L17: -2000
G18: ANEXO
G23: 3° Banco
G25: BANCO | L25: 119 - Banco Western Union do Brasil
G26: VALOR ATUAL | L26: 500000
G27: ANEXO

Sheet Planilha7
A1: bancos
A2: 1 - Banco do Brasil;
A3: 102 - XP Investimentos CCTVM S.A.
A4: 104 - Caixa Econômica Federal
A5: 119 - Banco Western Union do Brasil
A6: 184 - Banco Itaú BBA S.A.
A7: 197 - Stone Pagamentos
A8: 208 - Banco BTG Pactual
A9: 212 - Banco Original
A10: 218 - Banco Bonsucesso
A11: 229 - Banco Cruzeiro do Sul
A12: 237 - Banco Bradesco
... A51: 82 - Banco Topázio

Sheet PATRIMÔNIOS
G4: 3. NOTAS BANCÁRIAS OU ENTRATO DE HOLERITES
G5: São todos os valores de entrada e saída mês a mês.
G8: DATA | H8: CATEGORIA | I8: ENTRADA | J8: SAÍDA
G9: 45718 | H9: Casa | I9: 20000 | J9: 5
G10: 45718 | H10: Freela | I10: 10 | J10: 20
G11: 46001 | H11: saúde | I11: 2000 | J11: 1

Sheet MONTANTE LÍQUIDO
G4: 1.MONTANTE LÍQUIDO DO TÍTULAR E IMPOSTOS A PAGAR
G5: São todos os valores do montante líquido do títular e impostos a serem pagos
H9: DATA | I9: SAÍDAS | J9: ENTRADAS | K9: MONTANTE LÍQUIDO | L9: IMPOSTOS
H10: =PATRIMÔNIOS!G9 -> 45718 | I10: =PATRIMÔNIOS!J9 -> 5 | J10: =PATRIMÔNIOS!I9 -> 20000 | K10: =Tabela8[[#This Row],[ENTRADAS]]-Tabela8[[#This Row],[SAÍDAS]] -> 19995 | L10: =_xlfn.XLOOKUP(Tabela8[[#This Row],[MONTANTE LÍQUIDO ]],Planilha3!C1:C6,Planilha3!B1:B6,"",-1,1) -> 0.1
H11: =PATRIMÔNIOS!G10 -> 45718 | I11: =PATRIMÔNIOS!J10 -> 20 | J11: =PATRIMÔNIOS!I10 -> 10 | K11: =Tabela8[[#This Row],[ENTRADAS]]-Tabela8[[#This Row],[SAÍDAS]] -> -10 | L11: =_xlfn.XLOOKUP(Tabela8[[#This Row],[MONTANTE LÍQUIDO ]],Planilha3!C2:C7,Planilha3!B2:B7,"",-1,1) -> Negativo
H12: =PATRIMÔNIOS!G11 -> 46001 | I12: =PATRIMÔNIOS!J11 -> 1 | J12: =PATRIMÔNIOS!I11 -> 2000 | K12: =Tabela8[[#This Row],[ENTRADAS]]-Tabela8[[#This Row],[SAÍDAS]] -> 1999 | L12: =_xlfn.XLOOKUP(Tabela8[[#This Row],[MONTANTE LÍQUIDO ]],Planilha3!C3:C8,Planilha3!B3:B8,"",-1,1) -> Isento
H13: =PATRIMÔNIOS!G12 -> 0 | I13: =PATRIMÔNIOS!J12 -> 0 | J13: =PATRIMÔNIOS!I12 -> 0 | K13: =Tabela8[[#This Row],[ENTRADAS]]-Tabela8[[#This Row],[SAÍDAS]] -> 0 | L13: =_xlfn.XLOOKUP(Tabela8[[#This Row],[MONTANTE LÍQUIDO ]],Planilha3!C4:C9,Planilha3!B4:B9,"",-1,1)
H14: =PATRIMÔNIOS!G13 -> 0 | I14: =PATRIMÔNIOS!J13 -> 0 | J14: =PATRIMÔNIOS!I13 -> 0 | K14: =Tabela8[[#This Row],[ENTRADAS]]-Tabela8[[#This Row],[SAÍDAS]] -> 0 | L14: =_xlfn.XLOOKUP(Tabela8[[#This Row],[MONTANTE LÍQUIDO ]],Planilha3!C5:C10,Planilha3!B5:B10,"",-1,1)
H15: =PATRIMÔNIOS!G14 -> 0 | I15: =PATRIMÔNIOS!J14 -> 0 | J15: =PATRIMÔNIOS!I14 -> 0 | K15: =Tabela8[[#This Row],[ENTRADAS]]-Tabela8[[#This Row],[SAÍDAS]] -> 0 | L15: =_xlfn.XLOOKUP(Tabela8[[#This Row],[MONTANTE LÍQUIDO ]],Planilha3!C6:C11,Planilha3!B6:B11,"",-1,1)
H16: =PATRIMÔNIOS!G15 -> 0 | I16: =PATRIMÔNIOS!J15 -> 0 | J16: =PATRIMÔNIOS!I15 -> 0 | K16: =Tabela8[[#This Row],[ENTRADAS]]-Tabela8[[#This Row],[SAÍDAS]] -> 0 | L16: =_xlfn.XLOOKUP(Tabela8[[#This Row],[MONTANTE LÍQUIDO ]],Planilha3!C7:C12,Planilha3!B7:B12,"",-1,1)
H17: =PATRIMÔNIOS!G16 -> 0 | I17: =PATRIMÔNIOS!J16 -> 0 | J17: =PATRIMÔNIOS!I16 -> 0 | K17: =Tabela8[[#This Row],[ENTRADAS]]-Tabela8[[#This Row],[SAÍDAS]] -> 0 | L17: =_xlfn.XLOOKUP(Tabela8[[#This Row],[MONTANTE LÍQUIDO ]],Planilha3!C8:C13,Planilha3!B8:B13,"",-1,1)
H18: =PATRIMÔNIOS!G17 -> 0 | I18: =PATRIMÔNIOS!J17 -> 0 | J18: =PATRIMÔNIOS!I17 -> 0 | K18: =Tabela8[[#This Row],[ENTRADAS]]-Tabela8[[#This Row],[SAÍDAS]] -> 0 | L18: =_xlfn.XLOOKUP(Tabela8[[#This Row],[MONTANTE LÍQUIDO ]],Planilha3!C9:C14,Planilha3!B9:B14,"",-1,1)
H19: =PATRIMÔNIOS!G18 -> 0 | I19: =PATRIMÔNIOS!J18 -> 0 | J19: =PATRIMÔNIOS!I18 -> 0 | K19: =Tabela8[[#This Row],[ENTRADAS]]-Tabela8[[#This Row],[SAÍDAS]] -> 0 | L19: =_xlfn.XLOOKUP(Tabela8[[#This Row],[MONTANTE LÍQUIDO ]],Planilha3!C10:C15,Planilha3!B10:B15,"",-1,1)
H20: =PATRIMÔNIOS!G19 -> 0 | I20: =PATRIMÔNIOS!J19 -> 0 | J20: =PATRIMÔNIOS!I19 -> 0 | K20: =Tabela8[[#This Row],[ENTRADAS]]-Tabela8[[#This Row],[SAÍDAS]] -> 0 | L20: =_xlfn.XLOOKUP(Tabela8[[#This Row],[MONTANTE LÍQUIDO ]],Planilha3!C11:C16,Planilha3!B11:B16,"",-1,1)
H21: =PATRIMÔNIOS!G20 -> 0 | I21: =PATRIMÔNIOS!J20 -> 0 | J21: =PATRIMÔNIOS!I20 -> 0 | K21: =Tabela8[[#This Row],[ENTRADAS]]-Tabela8[[#This Row],[SAÍDAS]] -> 0 | L21: =_xlfn.XLOOKUP(Tabela8[[#This Row],[MONTANTE LÍQUIDO ]],Planilha3!C12:C17,Planilha3!B12:B17,"",-1,1)
... H25: =PATRIMÔNIOS!G24 -> 0 | I25: =PATRIMÔNIOS!J24 -> 0 | J25: =PATRIMÔNIOS!I24 -> 0 | K25: =Tabela8[[#This Row],[ENTRADAS]]-Tabela8[[#This Row],[SAÍDAS]] -> 0 | L25: =_xlfn.XLOOKUP(Tabela8[[#This Row],[MONTANTE LÍQUIDO ]],Planilha3!C16:C21,Planilha3!B16:B21,"",-1,1)

Sheet Planilha3
B1: impostos | C1: Valor
B2: Negativo | C2: -100000
B3: Isento | C3: 0
B4: 0.05 | C4: 5001
B5: 0.1 | C5: 10000
B6: 0.15 | C6: 20000
B7: 0.2 | C7: 30000
